verficar_cpf/__init__.py
verficar_cpf/verificar_cpf.py
verificar_cpf-0.0.1.dist-info/METADATA
verificar_cpf-0.0.1.dist-info/WHEEL
verificar_cpf-0.0.1.dist-info/top_level.txt
verificar_cpf-0.0.1.dist-info/RECORD
