Metadata-Version: 2.1
Name: verificar_cpf
Version: 0.0.1
Summary: Verifica se o número do CPF é válido
Author: Leonardo Diniz
Requires-Python: >=3.8
